api_permission/__init__.py
api_permission/admin.py
api_permission/api_settings.py
api_permission/apps.py
api_permission/exceptions.py
api_permission/middleware.py
api_permission/models.py
api_permission/serializers.py
api_permission/settings.py
api_permission/tests.py
api_permission/urls.py
api_permission/views.py
api_permission/migrations/0001_initial.py
api_permission/migrations/__init__.py
django_api_permission-0.0.4.dist-info/LICENSE
django_api_permission-0.0.4.dist-info/METADATA
django_api_permission-0.0.4.dist-info/WHEEL
django_api_permission-0.0.4.dist-info/top_level.txt
django_api_permission-0.0.4.dist-info/RECORD
